<?xml version="1.0" encoding="UTF-8"?>
<!DOCTYPE hibernate-mapping PUBLIC "-//Hibernate/Hibernate Mapping DTD//EN" "http://www.hibernate.org/dtd/hibernate-mapping-3.0.dtd">
<hibernate-mapping>

    <class  name="com.group4.ethazi_ad.modelo.clases.Cliente" table="Clients">
        <id name="id" column="id">
            <!--<generator class="increment" />-->
        </id>
        <property name="dni" />
        <property name="nick" />
        <property name="pass" />
        <property name="email" />
    </class>
</hibernate-mapping>